abp/__init__.py
abp/filters/__init__.py
abp/filters/diff_script.py
abp/filters/parser.py
abp/filters/render_script.py
abp/filters/renderer.py
abp/filters/rpy.py
abp/filters/sources.py
python_abp-0.1.0.dist-info/LICENSE
python_abp-0.1.0.dist-info/METADATA
python_abp-0.1.0.dist-info/WHEEL
python_abp-0.1.0.dist-info/entry_points.txt
python_abp-0.1.0.dist-info/top_level.txt
python_abp-0.1.0.dist-info/RECORD
