Metadata-Version: 2.1
Name: python-abp
Version: 0.1.0
Summary: A library for working with Adblock Plus filter lists.
Home-page: https://hg.adblockplus.org/python-abp/
Author: eyeo GmbH
Author-email: info@adblockplus.org
License: GPLv3
Keywords: filterlist adblockplus ABP
Platform: UNKNOWN
Classifier: Development Status :: 4 - Beta
Classifier: Intended Audience :: Developers
Classifier: License :: OSI Approved :: GNU General Public License v3 (GPLv3)
Classifier: Natural Language :: English
Classifier: Programming Language :: Python :: 2
Classifier: Programming Language :: Python :: 2.7
Classifier: Programming Language :: Python :: 3
Classifier: Programming Language :: Python :: 3.5
Classifier: Programming Language :: Python :: 3.6
Classifier: Operating System :: OS Independent
Classifier: Topic :: Software Development :: Libraries :: Python Modules
